fock_matrix.py
fock_matrix-0.0.1.dist-info/METADATA
fock_matrix-0.0.1.dist-info/WHEEL
fock_matrix-0.0.1.dist-info/top_level.txt
fock_matrix-0.0.1.dist-info/RECORD
