Metadata-Version: 2.1
Name: fock-matrix
Version: 0.0.1
Summary: fock matrix implementation
Home-page: https://github.com/Razer-07
Author: Rahul
Author-email: rajkrahul00@gmail.com
License: UNKNOWN
Platform: UNKNOWN
Classifier: Programming Language :: Python :: 3
Classifier: Programming Language :: Python :: 3.5
Classifier: License :: OSI Approved :: MIT License
Classifier: Operating System :: OS Independent
Requires-Dist: blessings (~=1.7)
Provides-Extra: dev
Requires-Dist: pytest (>=3.5) ; extra == 'dev'
